qutipy/__init__.py
qutipy/channels.py
qutipy/clifford.py
qutipy/distance.py
qutipy/entropies.py
qutipy/fermions.py
qutipy/fidelities.py
qutipy/gates.py
qutipy/general_functions.py
qutipy/linalg.py
qutipy/misc.py
qutipy/pauli.py
qutipy/protocols.py
qutipy/states.py
qutipy/su.py
qutipy/weyl.py
QuTIpy-0.1.0a0.dist-info/LICENSE
QuTIpy-0.1.0a0.dist-info/METADATA
QuTIpy-0.1.0a0.dist-info/WHEEL
QuTIpy-0.1.0a0.dist-info/top_level.txt
QuTIpy-0.1.0a0.dist-info/RECORD
