Metadata-Version: 2.1
Name: QuTIpy
Version: 0.1.0a0
Summary: A package to perform quantum information calculations
Home-page: https://github.com/sumeetkhatri/QuTIpy
Author: Sumeet Khatri
Author-email: khatri6000@gmail.com
Maintainer: Sumeet Khatri, Arnav Das
Maintainer-email: khatri6000@gmail.com
License: LGPLv3
Project-URL: GitHub, https://github.com/sumeetkhatri/QuTIpy
Project-URL: Homepage, https://arnav-das.gitbook.io/qutipy-quantum-theory-of-information-for-python
Project-URL: PyPi, https://pypi.org/project/QuTIpy
Project-URL: Author, https://sumeetkhatri.com
Keywords: qutipy quantum sdk
Classifier: License :: OSI Approved :: GNU Affero General Public License v3
Classifier: Development Status :: 1 - Planning
Classifier: Topic :: Communications
Classifier: Topic :: Scientific/Engineering :: Physics
Classifier: Intended Audience :: Science/Research
Classifier: Operating System :: Microsoft :: Windows
Classifier: Operating System :: MacOS
Classifier: Operating System :: POSIX :: Linux
Classifier: Programming Language :: Python :: 3
Classifier: Programming Language :: Python :: 3.4
Classifier: Programming Language :: Python :: 3.5
Classifier: Programming Language :: Python :: 3.6
Classifier: Programming Language :: Python :: 3.7
Classifier: Programming Language :: Python :: 3.8
Classifier: Programming Language :: Python :: 3.9
Classifier: Programming Language :: Python :: 3.10
Classifier: Programming Language :: Python :: 3.11
License-File: LICENSE
Requires-Dist: numpy (>=1.21.3)
Requires-Dist: scipy (==1.8.0)
Requires-Dist: sympy (==1.9)
Requires-Dist: cvxpy (==1.2.0)
Requires-Dist: pytest
